UTC_Insights/__init__.py
UTC_Insights-0.0.1.dist-info/METADATA
UTC_Insights-0.0.1.dist-info/WHEEL
UTC_Insights-0.0.1.dist-info/top_level.txt
UTC_Insights-0.0.1.dist-info/RECORD
